{"cameraMode":{"drawMode":0,"name":"Shaded","section":"Shading Mode"},"sceneLighting":true,"audioPlay":false,"sceneViewState":{"showFog":true,"showMaterialUpdate":false,"showSkybox":true,"showFlares":true,"showImageEffects":true,"showParticleSystems":true},"in2DMode":false,"pivot":{"x":8.792032241821289,"y":5.578831672668457,"z":-2.2342660427093508},"rotation":{"x":-0.12538188695907594,"y":0.33266448974609377,"z":0.04467647895216942,"w":0.93360435962677},"size":24.268207550048829,"orthographic":false}